ninja_snake_lib/__init__.py
ninja_snake_lib/decorators.py
ninja_snake_lib/event.py
ninja_snake_lib/json_formatter.py
ninja_snake_lib/log_formatter.py
ninja_snake_lib/read_dotenv.py
ninja_snake_lib/setup_correlation_id.py
ninja_snake_lib/tracker.py
ninja_snake_lib-0.2.1.dist-info/LICENSE
ninja_snake_lib-0.2.1.dist-info/METADATA
ninja_snake_lib-0.2.1.dist-info/WHEEL
ninja_snake_lib-0.2.1.dist-info/RECORD
