Metadata-Version: 2.1
Name: NINJA-SNAKE-LIB
Version: 0.2.1
Summary: Biblioteca utilitaria para projetos Python no Getninjas
License: BSD
Author: Carlos Sá
Author-email: carlos.sa@getninjas.com.br
Requires-Python: >=3.10,<4.0
Classifier: License :: OSI Approved :: BSD License
Classifier: License :: Other/Proprietary License
Classifier: Programming Language :: Python
Classifier: Programming Language :: Python :: 3
Classifier: Programming Language :: Python :: 3.10
Classifier: Programming Language :: Python :: 3.11
Classifier: Programming Language :: Python :: 3.12
Requires-Dist: contextvars (>=2.4,<3.0)
Requires-Dist: django (>=3.2.18,<4.0.0)
Requires-Dist: json-log-formatter (>=0.5.2,<0.6.0)
Requires-Dist: requests (>=2.31.0,<3.0.0)
Project-URL: Bug Tracker, https://github.com/getninjas/ninja-snake-lib/issues
Project-URL: Código, https://github.com/getninjas/ninja-snake-lib
